ugbib_modell/__init__.py
ugbib_modell/bibModell.py
ugbib_modell-1.2.7.dist-info/METADATA
ugbib_modell-1.2.7.dist-info/WHEEL
ugbib_modell-1.2.7.dist-info/licenses/LICENSE
ugbib_modell-1.2.7.dist-info/RECORD
