Metadata-Version: 2.4
Name: ugbib_modell
Version: 1.2.7
Summary: Modell Daten PostgreSQL
License: MIT License
License-File: LICENSE
Classifier: Development Status :: 5 - Production/Stable
Classifier: Programming Language :: Python :: 3
Classifier: Programming Language :: Python :: 3.10
Requires-Python: >=3.10
Requires-Dist: psycopg2-binary
Requires-Dist: ugbib-divers
